{"firm_id":"18899","name":"Major Ad Fetterman Post #57","parent":"","location":{"address":"3005 Main Ave\nHyannis, NE","lat":"41.99900","lng":" -101.76171"},"total_critical":2,"total_noncritical":0,"inspection_count":6,"inspections":[{"date":"20110607","facod":"1","inspection_type":"1","violations":{"critical":"0","noncritical":"0"},"followup":"2","inspector_number":"2"},{"date":"20110607","facod":"12","inspection_type":"1","violations":{"critical":"0","noncritical":"0"},"followup":"2","inspector_number":"2"},{"date":"20100818","facod":"1","inspection_type":"1","violations":{"critical":"0","noncritical":"0"},"followup":"2","inspector_number":"2"},{"date":"20100818","facod":"12","inspection_type":"1","violations":{"critical":"0","noncritical":"0"},"followup":"2","inspector_number":"2"},{"date":"20130107","facod":"1","inspection_type":"1","violations":{"critical":"1","noncritical":"0"},"followup":"2","inspector_number":"2"},{"date":"20130107","facod":"12","inspection_type":"1","violations":{"critical":"1","noncritical":"0"},"followup":"2","inspector_number":"2"}]}
