{"firm_id":"21294","name":"Sts Peter & Paul Church Bin","parent":"Sts Peter & Paul Church","location":{"address":"3623 X St\nOmaha, NE","lat":"41.19907","lng":" -95.96793"},"total_critical":4,"total_noncritical":8,"inspection_count":2,"inspections":[{"date":"20121228","facod":"1","inspection_type":"1","violations":{"critical":"2","noncritical":"4"},"followup":"2","inspector_number":"88"},{"date":"20121228","facod":"12","inspection_type":"1","violations":{"critical":"2","noncritical":"4"},"followup":"2","inspector_number":"88"}]}
