{"firm_id":"21568","name":"Norfolk Family YMCA","parent":"Norfolk Family YMCA","location":{"address":"301 W Benjamin Ave\nNorfolk, NE","lat":"42.04728","lng":" -97.41023"},"total_critical":4,"total_noncritical":8,"inspection_count":4,"inspections":[{"date":"20120419","facod":"4","inspection_type":"1","violations":{"critical":"0","noncritical":"3"},"followup":"2","inspector_number":"4"},{"date":"20101002","facod":"4","inspection_type":"1","violations":{"critical":"1","noncritical":"3"},"followup":"2","inspector_number":"4"},{"date":"20100624","facod":"4","inspection_type":"1","violations":{"critical":"1","noncritical":"1"},"followup":"2","inspector_number":"4"},{"date":"20130506","facod":"4","inspection_type":"1","violations":{"critical":"2","noncritical":"1"},"followup":"2","inspector_number":"4"}]}
