{"firm_id":"21784","name":"Lewis & Clark Jr High","parent":"Omaha Public Schools","location":{"address":"6901 Burt\nOmaha, NE","lat":"41.26689","lng":" -96.02163"},"total_critical":1,"total_noncritical":4,"inspection_count":6,"inspections":[{"date":"20120622","facod":"20","inspection_type":"1","violations":{"critical":"0","noncritical":"0"},"followup":"2","inspector_number":"80"},{"date":"20111129","facod":"20","inspection_type":"1","violations":{"critical":"0","noncritical":"1"},"followup":"2","inspector_number":"80"},{"date":"20110614","facod":"20","inspection_type":"1","violations":{"critical":"0","noncritical":"0"},"followup":"2","inspector_number":"80"},{"date":"20101210","facod":"20","inspection_type":"1","violations":{"critical":"0","noncritical":"1"},"followup":"2","inspector_number":"80"},{"date":"20100423","facod":"20","inspection_type":"1","violations":{"critical":"0","noncritical":"1"},"followup":"2","inspector_number":"80"},{"date":"20130305","facod":"20","inspection_type":"1","violations":{"critical":"1","noncritical":"1"},"followup":"2","inspector_number":"80"}]}
