{"firm_id":"2314","name":"Runza Drive Inns/America","parent":"Runza Drive Inn","location":{"address":"1119 N 6th\nBeatrice, NE","lat":"40.27755","lng":" -96.74662"},"total_critical":12,"total_noncritical":42,"inspection_count":3,"inspections":[{"date":"20111201","facod":"1","inspection_type":"1","violations":{"critical":"3","noncritical":"14"},"followup":"2","inspector_number":"14"},{"date":"20110111","facod":"1","inspection_type":"1","violations":{"critical":"3","noncritical":"13"},"followup":"2","inspector_number":"14"},{"date":"20130404","facod":"1","inspection_type":"1","violations":{"critical":"6","noncritical":"15"},"followup":"2","inspector_number":"14"}]}
