{"firm_id":"23585","name":"Restaurant Bar El Ranchito","parent":"El Ranchito Rest & Bar","location":{"address":"2101 Cornhusker Dr\nS Sioux City, NE","lat":"42.46764","lng":" -96.42749"},"total_critical":60,"total_noncritical":168,"inspection_count":28,"inspections":[{"date":"20120517","facod":"1","inspection_type":"1","violations":{"critical":"1","noncritical":"5"},"followup":"2","inspector_number":"10"},{"date":"20120517","facod":"9","inspection_type":"1","violations":{"critical":"1","noncritical":"5"},"followup":"2","inspector_number":"10"},{"date":"20120517","facod":"12","inspection_type":"1","violations":{"critical":"1","noncritical":"5"},"followup":"2","inspector_number":"10"},{"date":"20120517","facod":"13","inspection_type":"1","violations":{"critical":"1","noncritical":"5"},"followup":"2","inspector_number":"10"},{"date":"20111028","facod":"1","inspection_type":"1","violations":{"critical":"1","noncritical":"4"},"followup":"2","inspector_number":"10"},{"date":"20111028","facod":"9","inspection_type":"1","violations":{"critical":"1","noncritical":"4"},"followup":"2","inspector_number":"10"},{"date":"20111028","facod":"12","inspection_type":"1","violations":{"critical":"1","noncritical":"4"},"followup":"2","inspector_number":"10"},{"date":"20111028","facod":"13","inspection_type":"1","violations":{"critical":"1","noncritical":"4"},"followup":"2","inspector_number":"10"},{"date":"20110509","facod":"1","inspection_type":"1","violations":{"critical":"6","noncritical":"12"},"followup":"2","inspector_number":"10"},{"date":"20110509","facod":"9","inspection_type":"1","violations":{"critical":"6","noncritical":"12"},"followup":"2","inspector_number":"10"},{"date":"20110509","facod":"12","inspection_type":"1","violations":{"critical":"6","noncritical":"12"},"followup":"2","inspector_number":"10"},{"date":"20110509","facod":"13","inspection_type":"1","violations":{"critical":"6","noncritical":"12"},"followup":"2","inspector_number":"10"},{"date":"20101028","facod":"1","inspection_type":"1","violations":{"critical":"2","noncritical":"10"},"followup":"2","inspector_number":"10"},{"date":"20101028","facod":"9","inspection_type":"1","violations":{"critical":"2","noncritical":"10"},"followup":"2","inspector_number":"10"},{"date":"20101028","facod":"12","inspection_type":"1","violations":{"critical":"2","noncritical":"10"},"followup":"2","inspector_number":"10"},{"date":"20101028","facod":"13","inspection_type":"1","violations":{"critical":"2","noncritical":"10"},"followup":"2","inspector_number":"10"},{"date":"20100406","facod":"1","inspection_type":"1","violations":{"critical":"1","noncritical":"4"},"followup":"2","inspector_number":"10"},{"date":"20100406","facod":"9","inspection_type":"1","violations":{"critical":"1","noncritical":"4"},"followup":"2","inspector_number":"10"},{"date":"20100406","facod":"12","inspection_type":"1","violations":{"critical":"1","noncritical":"4"},"followup":"2","inspector_number":"10"},{"date":"20100406","facod":"13","inspection_type":"1","violations":{"critical":"1","noncritical":"4"},"followup":"2","inspector_number":"10"},{"date":"20121113","facod":"1","inspection_type":"1","violations":{"critical":"4","noncritical":"3"},"followup":"2","inspector_number":"10"},{"date":"20121113","facod":"9","inspection_type":"1","violations":{"critical":"4","noncritical":"3"},"followup":"2","inspector_number":"10"},{"date":"20121113","facod":"12","inspection_type":"1","violations":{"critical":"4","noncritical":"3"},"followup":"2","inspector_number":"10"},{"date":"20121113","facod":"13","inspection_type":"1","violations":{"critical":"4","noncritical":"3"},"followup":"2","inspector_number":"10"},{"date":"20130709","facod":"1","inspection_type":"1","violations":{"critical":"0","noncritical":"4"},"followup":"2","inspector_number":"10"},{"date":"20130709","facod":"9","inspection_type":"1","violations":{"critical":"0","noncritical":"4"},"followup":"2","inspector_number":"10"},{"date":"20130709","facod":"12","inspection_type":"1","violations":{"critical":"0","noncritical":"4"},"followup":"2","inspector_number":"10"},{"date":"20130709","facod":"13","inspection_type":"1","violations":{"critical":"0","noncritical":"4"},"followup":"2","inspector_number":"10"}]}
