{"firm_id":"24129","name":"Coca Cola Refreshments USA Inc.","parent":"Coca Cola Refreshments USA, Inc.","location":{"address":"2800 S 13th St\nNorfolk, NE","lat":"41.99674","lng":" -97.42673"},"total_critical":1,"total_noncritical":1,"inspection_count":3,"inspections":[{"date":"20110210","facod":"7","inspection_type":"1","violations":{"critical":"0","noncritical":"1"},"followup":"2","inspector_number":"4"},{"date":"20100208","facod":"7","inspection_type":"1","violations":{"critical":"0","noncritical":"0"},"followup":"2","inspector_number":"4"},{"date":"20120831","facod":"7","inspection_type":"1","violations":{"critical":"1","noncritical":"0"},"followup":"2","inspector_number":"4"}]}
