{"firm_id":"24960","name":"Pizza Hut #010795-010","parent":"Peak Interests LLC","location":{"address":"2411 Ave G\nKearney, NE","lat":"40.69897","lng":" -99.07206"},"total_critical":14,"total_noncritical":26,"inspection_count":10,"inspections":[{"date":"20120207","facod":"1","inspection_type":"1","violations":{"critical":"1","noncritical":"2"},"followup":"2","inspector_number":"7"},{"date":"20120207","facod":"4","inspection_type":"1","violations":{"critical":"1","noncritical":"2"},"followup":"2","inspector_number":"7"},{"date":"20110707","facod":"1","inspection_type":"1","violations":{"critical":"2","noncritical":"2"},"followup":"2","inspector_number":"7"},{"date":"20110707","facod":"4","inspection_type":"1","violations":{"critical":"2","noncritical":"2"},"followup":"2","inspector_number":"7"},{"date":"20100830","facod":"1","inspection_type":"1","violations":{"critical":"2","noncritical":"4"},"followup":"2","inspector_number":"7"},{"date":"20100830","facod":"4","inspection_type":"1","violations":{"critical":"2","noncritical":"4"},"followup":"2","inspector_number":"7"},{"date":"20121009","facod":"1","inspection_type":"1","violations":{"critical":"1","noncritical":"3"},"followup":"2","inspector_number":"7"},{"date":"20121009","facod":"4","inspection_type":"1","violations":{"critical":"1","noncritical":"3"},"followup":"2","inspector_number":"7"},{"date":"20130327","facod":"1","inspection_type":"1","violations":{"critical":"1","noncritical":"2"},"followup":"2","inspector_number":"7"},{"date":"20130327","facod":"4","inspection_type":"1","violations":{"critical":"1","noncritical":"2"},"followup":"2","inspector_number":"7"}]}
