{"firm_id":"26140","name":"Farmers Union Coop Supply","parent":"","location":{"address":"Main\nBurchard, NE","lat":"40.14694","lng":" -96.35031"},"total_critical":10,"total_noncritical":12,"inspection_count":4,"inspections":[{"date":"20111025","facod":"11","inspection_type":"1","violations":{"critical":"2","noncritical":"1"},"followup":"2","inspector_number":"14"},{"date":"20111025","facod":"14","inspection_type":"1","violations":{"critical":"2","noncritical":"1"},"followup":"2","inspector_number":"14"},{"date":"20100803","facod":"11","inspection_type":"1","violations":{"critical":"3","noncritical":"5"},"followup":"2","inspector_number":"14"},{"date":"20100803","facod":"14","inspection_type":"1","violations":{"critical":"3","noncritical":"5"},"followup":"2","inspector_number":"14"}]}
