{"firm_id":"29415","name":"Michaels Cantina","parent":"Ankle Deep Inc.","location":{"address":"912 Omaha Ave.\nNorfolk, NE","lat":"42.01826","lng":" -97.41966"},"total_critical":27,"total_noncritical":147,"inspection_count":15,"inspections":[{"date":"20120418","facod":"12","inspection_type":"1","violations":{"critical":"0","noncritical":"6"},"followup":"2","inspector_number":"4"},{"date":"20120411","facod":"1","inspection_type":"1","violations":{"critical":"4","noncritical":"7"},"followup":"2","inspector_number":"4"},{"date":"20120411","facod":"12","inspection_type":"1","violations":{"critical":"0","noncritical":"13"},"followup":"1","inspector_number":"4"},{"date":"20110902","facod":"1","inspection_type":"2","violations":{"critical":"0","noncritical":"6"},"followup":"2","inspector_number":"4"},{"date":"20110902","facod":"12","inspection_type":"2","violations":{"critical":"0","noncritical":"6"},"followup":"2","inspector_number":"4"},{"date":"20110824","facod":"1","inspection_type":"1","violations":{"critical":"0","noncritical":"19"},"followup":"1","inspector_number":"4"},{"date":"20110824","facod":"12","inspection_type":"1","violations":{"critical":"0","noncritical":"19"},"followup":"1","inspector_number":"4"},{"date":"20110127","facod":"1","inspection_type":"1","violations":{"critical":"2","noncritical":"11"},"followup":"2","inspector_number":"4"},{"date":"20110127","facod":"12","inspection_type":"1","violations":{"critical":"2","noncritical":"11"},"followup":"2","inspector_number":"4"},{"date":"20100713","facod":"1","inspection_type":"1","violations":{"critical":"3","noncritical":"10"},"followup":"2","inspector_number":"4"},{"date":"20100713","facod":"12","inspection_type":"1","violations":{"critical":"0","noncritical":"7"},"followup":"2","inspector_number":"4"},{"date":"20121101","facod":"1","inspection_type":"1","violations":{"critical":"6","noncritical":"7"},"followup":"2","inspector_number":"4"},{"date":"20121101","facod":"12","inspection_type":"1","violations":{"critical":"6","noncritical":"7"},"followup":"2","inspector_number":"4"},{"date":"20130516","facod":"1","inspection_type":"1","violations":{"critical":"2","noncritical":"9"},"followup":"2","inspector_number":"4"},{"date":"20130516","facod":"12","inspection_type":"1","violations":{"critical":"2","noncritical":"9"},"followup":"2","inspector_number":"4"}]}
