{"firm_id":"29631","name":"Walgreens #5360","parent":"Walgreen","location":{"address":"5062 S. 155th St\nOmaha, NE","lat":"41.20706","lng":" -96.15698"},"total_critical":4,"total_noncritical":1,"inspection_count":4,"inspections":[{"date":"20120111","facod":"2","inspection_type":"1","violations":{"critical":"1","noncritical":"0"},"followup":"2","inspector_number":"87"},{"date":"20120111","facod":"11","inspection_type":"1","violations":{"critical":"1","noncritical":"0"},"followup":"2","inspector_number":"87"},{"date":"20110105","facod":"11","inspection_type":"1","violations":{"critical":"1","noncritical":"1"},"followup":"2","inspector_number":"87"},{"date":"20100122","facod":"11","inspection_type":"1","violations":{"critical":"1","noncritical":"0"},"followup":"2","inspector_number":"87"}]}
