{"firm_id":"29909","name":"Cigarette Chain","parent":"Cigarette Chain Inc","location":{"address":"323 E Overland\nScottsbluff, NE","lat":"41.85933","lng":" -103.65754"},"total_critical":10,"total_noncritical":60,"inspection_count":5,"inspections":[{"date":"20120105","facod":"14","inspection_type":"2","violations":{"critical":"0","noncritical":"10"},"followup":"2","inspector_number":"1"},{"date":"20111219","facod":"14","inspection_type":"1","violations":{"critical":"4","noncritical":"17"},"followup":"1","inspector_number":"1"},{"date":"20110107","facod":"14","inspection_type":"1","violations":{"critical":"2","noncritical":"15"},"followup":"2","inspector_number":"1"},{"date":"20100104","facod":"14","inspection_type":"1","violations":{"critical":"1","noncritical":"14"},"followup":"2","inspector_number":"1"},{"date":"20121127","facod":"14","inspection_type":"1","violations":{"critical":"3","noncritical":"4"},"followup":"2","inspector_number":"1"}]}
