{"firm_id":"33222","name":"Kooper's Korner","parent":"","location":{"address":"149 Commercial Ave\nHildreth, NE","lat":"40.33862","lng":" -99.04357"},"total_critical":18,"total_noncritical":20,"inspection_count":16,"inspections":[{"date":"20120705","facod":"1","inspection_type":"1","violations":{"critical":"1","noncritical":"2"},"followup":"2","inspector_number":"12"},{"date":"20120705","facod":"12","inspection_type":"1","violations":{"critical":"1","noncritical":"2"},"followup":"2","inspector_number":"12"},{"date":"20120123","facod":"1","inspection_type":"1","violations":{"critical":"2","noncritical":"0"},"followup":"2","inspector_number":"12"},{"date":"20120123","facod":"12","inspection_type":"1","violations":{"critical":"2","noncritical":"0"},"followup":"2","inspector_number":"12"},{"date":"20110928","facod":"1","inspection_type":"1","violations":{"critical":"1","noncritical":"0"},"followup":"2","inspector_number":"12"},{"date":"20110928","facod":"12","inspection_type":"1","violations":{"critical":"1","noncritical":"0"},"followup":"2","inspector_number":"12"},{"date":"20110315","facod":"1","inspection_type":"1","violations":{"critical":"0","noncritical":"2"},"followup":"2","inspector_number":"12"},{"date":"20110315","facod":"12","inspection_type":"1","violations":{"critical":"0","noncritical":"2"},"followup":"2","inspector_number":"12"},{"date":"20101006","facod":"1","inspection_type":"1","violations":{"critical":"0","noncritical":"1"},"followup":"2","inspector_number":"12"},{"date":"20101006","facod":"12","inspection_type":"1","violations":{"critical":"0","noncritical":"1"},"followup":"2","inspector_number":"12"},{"date":"20100428","facod":"1","inspection_type":"1","violations":{"critical":"2","noncritical":"2"},"followup":"2","inspector_number":"12"},{"date":"20100428","facod":"12","inspection_type":"1","violations":{"critical":"2","noncritical":"2"},"followup":"2","inspector_number":"12"},{"date":"20130115","facod":"1","inspection_type":"1","violations":{"critical":"3","noncritical":"1"},"followup":"2","inspector_number":"12"},{"date":"20130115","facod":"12","inspection_type":"1","violations":{"critical":"3","noncritical":"1"},"followup":"2","inspector_number":"12"},{"date":"20130605","facod":"1","inspection_type":"1","violations":{"critical":"0","noncritical":"2"},"followup":"2","inspector_number":"12"},{"date":"20130605","facod":"12","inspection_type":"1","violations":{"critical":"0","noncritical":"2"},"followup":"2","inspector_number":"12"}]}
