{"firm_id":"33443","name":"Family Dollar Inc #5015","parent":"Family Dollar Inc.","location":{"address":"811 S Burlington Ave\nHastings, NE","lat":"40.57500","lng":" -98.39257"},"total_critical":6,"total_noncritical":2,"inspection_count":3,"inspections":[{"date":"20110818","facod":"11","inspection_type":"1","violations":{"critical":"1","noncritical":"1"},"followup":"2","inspector_number":"7"},{"date":"20100823","facod":"11","inspection_type":"1","violations":{"critical":"1","noncritical":"0"},"followup":"2","inspector_number":"7"},{"date":"20120830","facod":"11","inspection_type":"1","violations":{"critical":"4","noncritical":"1"},"followup":"2","inspector_number":"7"}]}
