{"firm_id":"35168","name":"Pop 'N Post","parent":"","location":{"address":"2843 Raymond Rd\nSeward, NE","lat":"40.95950","lng":" -97.10781"},"total_critical":0,"total_noncritical":3,"inspection_count":4,"inspections":[{"date":"20120430","facod":"6","inspection_type":"1","violations":{"critical":"0","noncritical":"3"},"followup":"2","inspector_number":"13"},{"date":"20110615","facod":"6","inspection_type":"1","violations":{"critical":"0","noncritical":"0"},"followup":"2","inspector_number":"13"},{"date":"20100611","facod":"6","inspection_type":"1","violations":{"critical":"0","noncritical":"0"},"followup":"2","inspector_number":"13"},{"date":"20130410","facod":"6","inspection_type":"1","violations":{"critical":"0","noncritical":"0"},"followup":"2","inspector_number":"13"}]}
