{"firm_id":"3536","name":"Big Reds Cafe & Lounge","parent":"","location":{"address":"W Hwy 2\nMullen, NE","lat":"42.04334","lng":" -101.04247"},"total_critical":12,"total_noncritical":64,"inspection_count":18,"inspections":[{"date":"20120521","facod":"1","inspection_type":"1","violations":{"critical":"1","noncritical":"4"},"followup":"2","inspector_number":"2"},{"date":"20120521","facod":"12","inspection_type":"1","violations":{"critical":"1","noncritical":"4"},"followup":"2","inspector_number":"2"},{"date":"20120104","facod":"1","inspection_type":"1","violations":{"critical":"1","noncritical":"3"},"followup":"2","inspector_number":"2"},{"date":"20120104","facod":"12","inspection_type":"1","violations":{"critical":"1","noncritical":"3"},"followup":"2","inspector_number":"2"},{"date":"20110802","facod":"1","inspection_type":"1","violations":{"critical":"1","noncritical":"3"},"followup":"2","inspector_number":"2"},{"date":"20110802","facod":"12","inspection_type":"1","violations":{"critical":"1","noncritical":"3"},"followup":"2","inspector_number":"2"},{"date":"20110301","facod":"1","inspection_type":"1","violations":{"critical":"1","noncritical":"4"},"followup":"2","inspector_number":"2"},{"date":"20110301","facod":"12","inspection_type":"1","violations":{"critical":"1","noncritical":"4"},"followup":"2","inspector_number":"2"},{"date":"20101123","facod":"1","inspection_type":"1","violations":{"critical":"0","noncritical":"3"},"followup":"2","inspector_number":"2"},{"date":"20101123","facod":"12","inspection_type":"1","violations":{"critical":"0","noncritical":"3"},"followup":"2","inspector_number":"2"},{"date":"20100707","facod":"1","inspection_type":"1","violations":{"critical":"1","noncritical":"4"},"followup":"2","inspector_number":"2"},{"date":"20100707","facod":"12","inspection_type":"1","violations":{"critical":"1","noncritical":"4"},"followup":"2","inspector_number":"2"},{"date":"20100125","facod":"1","inspection_type":"1","violations":{"critical":"0","noncritical":"2"},"followup":"2","inspector_number":"2"},{"date":"20100125","facod":"12","inspection_type":"1","violations":{"critical":"0","noncritical":"2"},"followup":"2","inspector_number":"2"},{"date":"20121017","facod":"1","inspection_type":"1","violations":{"critical":"0","noncritical":"5"},"followup":"2","inspector_number":"2"},{"date":"20121017","facod":"12","inspection_type":"1","violations":{"critical":"0","noncritical":"5"},"followup":"2","inspector_number":"2"},{"date":"20130305","facod":"1","inspection_type":"1","violations":{"critical":"1","noncritical":"4"},"followup":"2","inspector_number":"2"},{"date":"20130305","facod":"12","inspection_type":"1","violations":{"critical":"1","noncritical":"4"},"followup":"2","inspector_number":"2"}]}
