{"firm_id":"35403","name":"Dad's Bar & Grill","parent":"Dad's Bar & Grill LLC","location":{"address":"1220 16th Ave, Box 145\nMitchell, NE","lat":"41.93950","lng":" -103.81009"},"total_critical":30,"total_noncritical":24,"inspection_count":6,"inspections":[{"date":"20110120","facod":"1","inspection_type":"1","violations":{"critical":"4","noncritical":"2"},"followup":"2","inspector_number":"1"},{"date":"20110120","facod":"12","inspection_type":"1","violations":{"critical":"4","noncritical":"2"},"followup":"2","inspector_number":"1"},{"date":"20100929","facod":"1","inspection_type":"1","violations":{"critical":"6","noncritical":"3"},"followup":"2","inspector_number":"1"},{"date":"20100929","facod":"12","inspection_type":"1","violations":{"critical":"6","noncritical":"3"},"followup":"2","inspector_number":"1"},{"date":"20100401","facod":"1","inspection_type":"1","violations":{"critical":"5","noncritical":"7"},"followup":"2","inspector_number":"1"},{"date":"20100401","facod":"12","inspection_type":"1","violations":{"critical":"5","noncritical":"7"},"followup":"2","inspector_number":"1"}]}
