{"firm_id":"36751","name":"Rath's Mini Mart","parent":"","location":{"address":"206 Hwy 20\nLaurel, NE","lat":"42.42906","lng":" -97.09601"},"total_critical":2,"total_noncritical":36,"inspection_count":8,"inspections":[{"date":"20120210","facod":"1","inspection_type":"1","violations":{"critical":"0","noncritical":"4"},"followup":"2","inspector_number":"10"},{"date":"20120210","facod":"11","inspection_type":"1","violations":{"critical":"0","noncritical":"4"},"followup":"2","inspector_number":"10"},{"date":"20110908","facod":"1","inspection_type":"1","violations":{"critical":"1","noncritical":"10"},"followup":"2","inspector_number":"10"},{"date":"20110908","facod":"11","inspection_type":"1","violations":{"critical":"1","noncritical":"10"},"followup":"2","inspector_number":"10"},{"date":"20120906","facod":"1","inspection_type":"1","violations":{"critical":"0","noncritical":"2"},"followup":"2","inspector_number":"10"},{"date":"20120906","facod":"11","inspection_type":"1","violations":{"critical":"0","noncritical":"2"},"followup":"2","inspector_number":"10"},{"date":"20130502","facod":"1","inspection_type":"1","violations":{"critical":"0","noncritical":"2"},"followup":"2","inspector_number":"10"},{"date":"20130502","facod":"11","inspection_type":"1","violations":{"critical":"0","noncritical":"2"},"followup":"2","inspector_number":"10"}]}
