{"firm_id":"36998","name":"Camelot Friendship Center","parent":"Eastern Nebraska Office of Aging","location":{"address":"9270 Cady Ave\nOmaha, NE","lat":"41.28021","lng":" -96.05669"},"total_critical":5,"total_noncritical":1,"inspection_count":4,"inspections":[{"date":"20120522","facod":"22","inspection_type":"1","violations":{"critical":"0","noncritical":"0"},"followup":"2","inspector_number":"80"},{"date":"20110801","facod":"22","inspection_type":"1","violations":{"critical":"1","noncritical":"0"},"followup":"2","inspector_number":"80"},{"date":"20100715","facod":"22","inspection_type":"1","violations":{"critical":"1","noncritical":"0"},"followup":"2","inspector_number":"80"},{"date":"20130703","facod":"22","inspection_type":"1","violations":{"critical":"3","noncritical":"1"},"followup":"2","inspector_number":"80"}]}
