{"firm_id":"37249","name":"Ruby Tuesday #7249","parent":"Ruby Tuesday Corp","location":{"address":"3429 West 13th St\nGrand Island, NE","lat":"40.93146","lng":" -98.38260"},"total_critical":46,"total_noncritical":88,"inspection_count":18,"inspections":[{"date":"20120215","facod":"1","inspection_type":"1","violations":{"critical":"0","noncritical":"1"},"followup":"2","inspector_number":"73"},{"date":"20120215","facod":"12","inspection_type":"1","violations":{"critical":"0","noncritical":"1"},"followup":"2","inspector_number":"73"},{"date":"20120112","facod":"1","inspection_type":"2","violations":{"critical":"1","noncritical":"2"},"followup":"2","inspector_number":"73"},{"date":"20120112","facod":"12","inspection_type":"2","violations":{"critical":"1","noncritical":"2"},"followup":"2","inspector_number":"73"},{"date":"20111219","facod":"1","inspection_type":"1","violations":{"critical":"6","noncritical":"12"},"followup":"1","inspector_number":"73"},{"date":"20111219","facod":"1","inspection_type":"1","violations":{"critical":"6","noncritical":"12"},"followup":"2","inspector_number":"73"},{"date":"20111219","facod":"12","inspection_type":"1","violations":{"critical":"6","noncritical":"12"},"followup":"1","inspector_number":"73"},{"date":"20111219","facod":"12","inspection_type":"1","violations":{"critical":"6","noncritical":"12"},"followup":"2","inspector_number":"73"},{"date":"20110712","facod":"1","inspection_type":"2","violations":{"critical":"1","noncritical":"0"},"followup":"2","inspector_number":"73"},{"date":"20110712","facod":"12","inspection_type":"2","violations":{"critical":"1","noncritical":"0"},"followup":"2","inspector_number":"73"},{"date":"20110627","facod":"1","inspection_type":"3","violations":{"critical":"3","noncritical":"4"},"followup":"2","inspector_number":"73"},{"date":"20110627","facod":"12","inspection_type":"3","violations":{"critical":"3","noncritical":"4"},"followup":"2","inspector_number":"73"},{"date":"20110208","facod":"1","inspection_type":"1","violations":{"critical":"0","noncritical":"4"},"followup":"2","inspector_number":"73"},{"date":"20110208","facod":"12","inspection_type":"1","violations":{"critical":"0","noncritical":"4"},"followup":"2","inspector_number":"73"},{"date":"20120809","facod":"1","inspection_type":"1","violations":{"critical":"2","noncritical":"4"},"followup":"2","inspector_number":"73"},{"date":"20120809","facod":"12","inspection_type":"1","violations":{"critical":"2","noncritical":"4"},"followup":"2","inspector_number":"73"},{"date":"20130128","facod":"1","inspection_type":"1","violations":{"critical":"4","noncritical":"5"},"followup":"2","inspector_number":"73"},{"date":"20130128","facod":"12","inspection_type":"1","violations":{"critical":"4","noncritical":"5"},"followup":"2","inspector_number":"73"}]}
