{"firm_id":"37351","name":"Dudek Company","parent":"","location":{"address":"123 N Main\nGordon, NE","lat":"42.80364","lng":" -102.20323"},"total_critical":0,"total_noncritical":11,"inspection_count":3,"inspections":[{"date":"20120309","facod":"6","inspection_type":"1","violations":{"critical":"0","noncritical":"4"},"followup":"2","inspector_number":"1"},{"date":"20110318","facod":"6","inspection_type":"1","violations":{"critical":"0","noncritical":"3"},"followup":"2","inspector_number":"1"},{"date":"20101001","facod":"6","inspection_type":"1","violations":{"critical":"0","noncritical":"4"},"followup":"2","inspector_number":"1"}]}
