{"firm_id":"37442","name":"Home Cooking at it's Finest","parent":"","location":{"address":"3156 32nd Rd\nSilver Creek, NE","lat":"41.31876","lng":" -97.69479"},"total_critical":1,"total_noncritical":0,"inspection_count":3,"inspections":[{"date":"20110415","facod":"16","inspection_type":"1","violations":{"critical":"1","noncritical":"0"},"followup":"2","inspector_number":"8"},{"date":"20100427","facod":"16","inspection_type":"1","violations":{"critical":"0","noncritical":"0"},"followup":"2","inspector_number":"8"},{"date":"20120807","facod":"16","inspection_type":"1","violations":{"critical":"0","noncritical":"0"},"followup":"2","inspector_number":"8"}]}
