{"firm_id":"37487","name":"Chipotle","parent":"Chipotle Mexican Grill","location":{"address":"2717 S 177th St\nOmaha, NE","lat":"41.23324","lng":" -96.19241"},"total_critical":3,"total_noncritical":2,"inspection_count":5,"inspections":[{"date":"20111004","facod":"1","inspection_type":"2","violations":{"critical":"0","noncritical":"1"},"followup":"2","inspector_number":"86"},{"date":"20110307","facod":"1","inspection_type":"1","violations":{"critical":"1","noncritical":"0"},"followup":"2","inspector_number":"86"},{"date":"20100907","facod":"1","inspection_type":"1","violations":{"critical":"0","noncritical":"0"},"followup":"2","inspector_number":"86"},{"date":"20100329","facod":"1","inspection_type":"1","violations":{"critical":"0","noncritical":"0"},"followup":"2","inspector_number":"86"},{"date":"20130211","facod":"1","inspection_type":"1","violations":{"critical":"2","noncritical":"1"},"followup":"2","inspector_number":"86"}]}
