{"firm_id":"37707","name":"Red Square","parent":"Red Square Inc.","location":{"address":"423 S 11th St\nOmaha, NE","lat":"41.25623","lng":" -95.93049"},"total_critical":0,"total_noncritical":9,"inspection_count":2,"inspections":[{"date":"20120104","facod":"11","inspection_type":"1","violations":{"critical":"0","noncritical":"7"},"followup":"2","inspector_number":"84"},{"date":"20121120","facod":"11","inspection_type":"1","violations":{"critical":"0","noncritical":"2"},"followup":"2","inspector_number":"84"}]}
