{"firm_id":"37852","name":"Kracky McGee's-Simply Scumptious","parent":"GPMM Inc.","location":{"address":"4501 Abbott Dr\nOmaha, NE","lat":"41.29505","lng":" -95.90068"},"total_critical":14,"total_noncritical":34,"inspection_count":8,"inspections":[{"date":"20110916","facod":"1","inspection_type":"1","violations":{"critical":"2","noncritical":"5"},"followup":"2","inspector_number":"81"},{"date":"20110916","facod":"5","inspection_type":"1","violations":{"critical":"2","noncritical":"5"},"followup":"2","inspector_number":"81"},{"date":"20110127","facod":"1","inspection_type":"1","violations":{"critical":"2","noncritical":"3"},"followup":"2","inspector_number":"81"},{"date":"20110127","facod":"5","inspection_type":"1","violations":{"critical":"2","noncritical":"3"},"followup":"2","inspector_number":"81"},{"date":"20100407","facod":"1","inspection_type":"1","violations":{"critical":"1","noncritical":"4"},"followup":"2","inspector_number":"81"},{"date":"20100407","facod":"5","inspection_type":"1","violations":{"critical":"1","noncritical":"4"},"followup":"2","inspector_number":"81"},{"date":"20121115","facod":"1","inspection_type":"1","violations":{"critical":"2","noncritical":"5"},"followup":"2","inspector_number":"81"},{"date":"20121115","facod":"5","inspection_type":"1","violations":{"critical":"2","noncritical":"5"},"followup":"2","inspector_number":"81"}]}
