{"firm_id":"38067","name":"Charlie's Station","parent":"Charlie's Station of Elba LLC","location":{"address":"1734 Hwy 11\nElba, NE","lat":"41.28455","lng":" -98.57298"},"total_critical":14,"total_noncritical":44,"inspection_count":12,"inspections":[{"date":"20120329","facod":"1","inspection_type":"1","violations":{"critical":"2","noncritical":"4"},"followup":"2","inspector_number":"2"},{"date":"20120329","facod":"11","inspection_type":"1","violations":{"critical":"2","noncritical":"4"},"followup":"2","inspector_number":"2"},{"date":"20111115","facod":"1","inspection_type":"1","violations":{"critical":"1","noncritical":"3"},"followup":"2","inspector_number":"2"},{"date":"20111115","facod":"11","inspection_type":"1","violations":{"critical":"1","noncritical":"3"},"followup":"2","inspector_number":"2"},{"date":"20110601","facod":"1","inspection_type":"1","violations":{"critical":"2","noncritical":"3"},"followup":"2","inspector_number":"2"},{"date":"20110601","facod":"11","inspection_type":"1","violations":{"critical":"2","noncritical":"3"},"followup":"2","inspector_number":"2"},{"date":"20101129","facod":"1","inspection_type":"1","violations":{"critical":"1","noncritical":"3"},"followup":"2","inspector_number":"2"},{"date":"20101129","facod":"11","inspection_type":"1","violations":{"critical":"1","noncritical":"3"},"followup":"2","inspector_number":"2"},{"date":"20120912","facod":"1","inspection_type":"1","violations":{"critical":"1","noncritical":"4"},"followup":"2","inspector_number":"2"},{"date":"20120912","facod":"11","inspection_type":"1","violations":{"critical":"1","noncritical":"4"},"followup":"2","inspector_number":"2"},{"date":"20130520","facod":"1","inspection_type":"1","violations":{"critical":"0","noncritical":"5"},"followup":"2","inspector_number":"2"},{"date":"20130520","facod":"11","inspection_type":"1","violations":{"critical":"0","noncritical":"5"},"followup":"2","inspector_number":"2"}]}
