{"firm_id":"39253","name":"UR Grocery","parent":"","location":{"address":"1820 P St\nLincoln, NE","lat":"40.81471","lng":" -96.69466"},"total_critical":10,"total_noncritical":17,"inspection_count":4,"inspections":[{"date":"20120412","facod":"3","inspection_type":"1","violations":{"critical":"0","noncritical":"7"},"followup":"2","inspector_number":"63"},{"date":"20120904","facod":"3","inspection_type":"5","violations":{"critical":"0","noncritical":"0"},"followup":"2","inspector_number":"63"},{"date":"20130423","facod":"3","inspection_type":"1","violations":{"critical":"5","noncritical":"5"},"followup":"2","inspector_number":"63"},{"date":"20130423","facod":"6","inspection_type":"1","violations":{"critical":"5","noncritical":"5"},"followup":"2","inspector_number":"63"}]}
