{"firm_id":"41035","name":"Heartland Public Shooting Park","parent":"City of Grand Island","location":{"address":"6788 W Husker Hwy\nAlda, NE","lat":"40.88775","lng":" -98.47392"},"total_critical":2,"total_noncritical":1,"inspection_count":2,"inspections":[{"date":"20110413","facod":"1","inspection_type":"1","violations":{"critical":"0","noncritical":"1"},"followup":"2","inspector_number":"73"},{"date":"20130419","facod":"1","inspection_type":"1","violations":{"critical":"2","noncritical":"0"},"followup":"2","inspector_number":"73"}]}
