{"firm_id":"42498","name":"Taco Johns","parent":"Bremer Restaurant Management","location":{"address":"1115 S Saddle Creek Rd\nOmaha, NE","lat":"41.24830","lng":" -95.98832"},"total_critical":5,"total_noncritical":24,"inspection_count":6,"inspections":[{"date":"20120112","facod":"1","inspection_type":"1","violations":{"critical":"1","noncritical":"4"},"followup":"2","inspector_number":"85"},{"date":"20110708","facod":"1","inspection_type":"1","violations":{"critical":"2","noncritical":"7"},"followup":"2","inspector_number":"85"},{"date":"20110107","facod":"1","inspection_type":"1","violations":{"critical":"1","noncritical":"4"},"followup":"2","inspector_number":"85"},{"date":"20100708","facod":"1","inspection_type":"1","violations":{"critical":"0","noncritical":"5"},"followup":"2","inspector_number":"85"},{"date":"20100121","facod":"1","inspection_type":"1","violations":{"critical":"0","noncritical":"4"},"followup":"2","inspector_number":"85"},{"date":"20130418","facod":"1","inspection_type":"1","violations":{"critical":"1","noncritical":"0"},"followup":"2","inspector_number":"85"}]}
