{"firm_id":"42792","name":"Frito Lay Inc. District 804","parent":"Frito-Lay Inc.","location":{"address":"1401 S Pine Industrial Rd\nNorfolk, NE","lat":"42.01705","lng":" -97.40094"},"total_critical":0,"total_noncritical":0,"inspection_count":2,"inspections":[{"date":"20110214","facod":"7","inspection_type":"1","violations":{"critical":"0","noncritical":"0"},"followup":"2","inspector_number":"4"},{"date":"20120815","facod":"7","inspection_type":"1","violations":{"critical":"0","noncritical":"0"},"followup":"2","inspector_number":"4"}]}
