{"firm_id":"43477","name":"Mr. Goodcents Subs & Pastas","parent":"RCCents Inc.","location":{"address":"759 N 114th St\nOmaha, NE","lat":"41.26735","lng":" -96.09184"},"total_critical":14,"total_noncritical":37,"inspection_count":15,"inspections":[{"date":"20120403","facod":"1","inspection_type":"1","violations":{"critical":"0","noncritical":"2"},"followup":"2","inspector_number":"82"},{"date":"20120403","facod":"16","inspection_type":"1","violations":{"critical":"0","noncritical":"2"},"followup":"2","inspector_number":"82"},{"date":"20111014","facod":"1","inspection_type":"1","violations":{"critical":"0","noncritical":"0"},"followup":"2","inspector_number":"82"},{"date":"20111014","facod":"16","inspection_type":"1","violations":{"critical":"0","noncritical":"0"},"followup":"2","inspector_number":"82"},{"date":"20110412","facod":"1","inspection_type":"1","violations":{"critical":"2","noncritical":"4"},"followup":"2","inspector_number":"82"},{"date":"20110412","facod":"16","inspection_type":"1","violations":{"critical":"2","noncritical":"4"},"followup":"2","inspector_number":"82"},{"date":"20110104","facod":"1","inspection_type":"1","violations":{"critical":"0","noncritical":"1"},"followup":"2","inspector_number":"82"},{"date":"20110104","facod":"16","inspection_type":"1","violations":{"critical":"0","noncritical":"1"},"followup":"2","inspector_number":"82"},{"date":"20101005","facod":"1","inspection_type":"1","violations":{"critical":"2","noncritical":"5"},"followup":"2","inspector_number":"82"},{"date":"20100329","facod":"1","inspection_type":"1","violations":{"critical":"2","noncritical":"4"},"followup":"2","inspector_number":"82"},{"date":"20100329","facod":"16","inspection_type":"1","violations":{"critical":"2","noncritical":"4"},"followup":"2","inspector_number":"82"},{"date":"20121030","facod":"1","inspection_type":"1","violations":{"critical":"0","noncritical":"2"},"followup":"2","inspector_number":"82"},{"date":"20121030","facod":"16","inspection_type":"1","violations":{"critical":"0","noncritical":"2"},"followup":"2","inspector_number":"82"},{"date":"20130520","facod":"1","inspection_type":"1","violations":{"critical":"2","noncritical":"3"},"followup":"2","inspector_number":"82"},{"date":"20130520","facod":"16","inspection_type":"1","violations":{"critical":"2","noncritical":"3"},"followup":"2","inspector_number":"82"}]}
