{"firm_id":"44629","name":"Great River Buffet","parent":"YW Zhang Garden LLC","location":{"address":"346 N Saddle Creek Rd\nOmaha, NE","lat":"41.26122","lng":" -95.98046"},"total_critical":17,"total_noncritical":15,"inspection_count":2,"inspections":[{"date":"20121207","facod":"1","inspection_type":"1","violations":{"critical":"13","noncritical":"12"},"followup":"1","inspector_number":"84"},{"date":"20121217","facod":"1","inspection_type":"2","violations":{"critical":"4","noncritical":"3"},"followup":"2","inspector_number":"84"}]}
