{"firm_id":"45610","name":"Olive Garden Italian Restaurant #4416","parent":"GRMI Inc","location":{"address":"1010 Allen Dr\nGrand Island, NE","lat":"40.92818","lng":" -98.38209"},"total_critical":4,"total_noncritical":4,"inspection_count":4,"inspections":[{"date":"20130129","facod":"1","inspection_type":"1","violations":{"critical":"2","noncritical":"1"},"followup":"2","inspector_number":"73"},{"date":"20130129","facod":"12","inspection_type":"1","violations":{"critical":"2","noncritical":"1"},"followup":"2","inspector_number":"73"},{"date":"20130726","facod":"1","inspection_type":"1","violations":{"critical":"0","noncritical":"1"},"followup":"2","inspector_number":"73"},{"date":"20130726","facod":"12","inspection_type":"1","violations":{"critical":"0","noncritical":"1"},"followup":"2","inspector_number":"73"}]}
