{"firm_id":"955","name":"Maplewood Lanes","parent":"Battiato, John J","location":{"address":"3030 N 101st\nOmaha, NE","lat":"41.28596","lng":" -96.07002"},"total_critical":22,"total_noncritical":72,"inspection_count":14,"inspections":[{"date":"20120202","facod":"1","inspection_type":"1","violations":{"critical":"1","noncritical":"6"},"followup":"2","inspector_number":"81"},{"date":"20120202","facod":"12","inspection_type":"1","violations":{"critical":"1","noncritical":"6"},"followup":"2","inspector_number":"81"},{"date":"20110815","facod":"1","inspection_type":"1","violations":{"critical":"0","noncritical":"7"},"followup":"2","inspector_number":"81"},{"date":"20110815","facod":"12","inspection_type":"1","violations":{"critical":"0","noncritical":"7"},"followup":"2","inspector_number":"81"},{"date":"20110215","facod":"1","inspection_type":"1","violations":{"critical":"2","noncritical":"3"},"followup":"2","inspector_number":"81"},{"date":"20110215","facod":"12","inspection_type":"1","violations":{"critical":"2","noncritical":"3"},"followup":"2","inspector_number":"81"},{"date":"20100818","facod":"1","inspection_type":"1","violations":{"critical":"3","noncritical":"5"},"followup":"2","inspector_number":"81"},{"date":"20100818","facod":"12","inspection_type":"1","violations":{"critical":"3","noncritical":"5"},"followup":"2","inspector_number":"81"},{"date":"20100217","facod":"1","inspection_type":"1","violations":{"critical":"3","noncritical":"5"},"followup":"2","inspector_number":"81"},{"date":"20100217","facod":"12","inspection_type":"1","violations":{"critical":"3","noncritical":"5"},"followup":"2","inspector_number":"81"},{"date":"20120920","facod":"1","inspection_type":"1","violations":{"critical":"0","noncritical":"6"},"followup":"2","inspector_number":"81"},{"date":"20120920","facod":"12","inspection_type":"1","violations":{"critical":"0","noncritical":"6"},"followup":"2","inspector_number":"81"},{"date":"20130501","facod":"1","inspection_type":"1","violations":{"critical":"2","noncritical":"4"},"followup":"2","inspector_number":"81"},{"date":"20130501","facod":"12","inspection_type":"1","violations":{"critical":"2","noncritical":"4"},"followup":"2","inspector_number":"81"}]}
